cos/__init__.py
cos/__main__.py
cos/auth.py
cos/cli.py
cos/client.py
cos/config.py
cos/constants.py
cos/exceptions.py
cos/transfer.py
cos/utils.py
cos/commands/__init__.py
cos/commands/configure.py
cos/commands/cors.py
cos/commands/cp.py
cos/commands/lifecycle.py
cos/commands/ls.py
cos/commands/mb.py
cos/commands/mv.py
cos/commands/policy.py
cos/commands/presign.py
cos/commands/rb.py
cos/commands/rm.py
cos/commands/sync.py
cos/commands/token.py
cos/commands/versioning.py
cos/tools/__init__.py
cos/tools/diagnose_ssl.py
tencent_cos_cli-2.2.1.dist-info/METADATA
tencent_cos_cli-2.2.1.dist-info/WHEEL
tencent_cos_cli-2.2.1.dist-info/entry_points.txt
tencent_cos_cli-2.2.1.dist-info/licenses/LICENSE
tencent_cos_cli-2.2.1.dist-info/RECORD
