Metadata-Version: 2.4
Name: tencent-cos-cli
Version: 2.2.1
Summary: Command line interface for Tencent Cloud Object Storage
Project-URL: Homepage, https://github.com/sszhu/coscli
Project-URL: Documentation, https://github.com/sszhu/coscli/blob/main/README.md
Project-URL: Repository, https://github.com/sszhu/coscli
Project-URL: Issues, https://github.com/sszhu/coscli/issues
Project-URL: Changelog, https://github.com/sszhu/coscli/blob/main/CHANGELOG.md
Author-email: Shanshan Zhu <sszhu.soft@gmail.com>
License: MIT
License-File: LICENSE
Keywords: cli,cloud,cos,object-storage,storage,tencent
Classifier: Development Status :: 5 - Production/Stable
Classifier: Intended Audience :: Developers
Classifier: Intended Audience :: System Administrators
Classifier: License :: OSI Approved :: MIT License
Classifier: Programming Language :: Python :: 3
Classifier: Programming Language :: Python :: 3.8
Classifier: Programming Language :: Python :: 3.9
Classifier: Programming Language :: Python :: 3.10
Classifier: Programming Language :: Python :: 3.11
Classifier: Programming Language :: Python :: 3.12
Classifier: Topic :: System :: Archiving
Classifier: Topic :: Utilities
Requires-Python: >=3.8
Requires-Dist: click>=8.1.0
Requires-Dist: configparser>=6.0.0
Requires-Dist: cos-python-sdk-v5>=1.9.30
Requires-Dist: pip>=25.0.1
Requires-Dist: pylint>=3.2.7
Requires-Dist: pytest>=8.3.5
Requires-Dist: rich>=13.0.0
Requires-Dist: streamlit>=1.40.1
Requires-Dist: tabulate>=0.9.0
Requires-Dist: tencentcloud-sdk-python>=3.0.1000
Requires-Dist: twine>=6.1.0
Provides-Extra: dev
Requires-Dist: black>=23.0.0; extra == 'dev'
Requires-Dist: mypy>=1.5.0; extra == 'dev'
Requires-Dist: pytest-cov>=4.1.0; extra == 'dev'
Requires-Dist: pytest-mock>=3.12.0; extra == 'dev'
Requires-Dist: pytest>=7.4.0; extra == 'dev'
Requires-Dist: ruff>=0.1.0; extra == 'dev'
